{
  "companies": [
    {
      "id": 1,
      "name": "TechNova",
      "cash": 500000,
      "valuation": 5000000,
      "burnRate": 50000,
      "employees": 12,
      "marketShare": 5,
      "growthRate": 12,
      "investorPressure": 7,
      "customerSatisfaction": 80
    }
  ],
  "marketConditions": [
    {
      "id": 1,
      "competitionLevel": 8,
      "economicClimate": "Recession",
      "industryGrowth": 6,
      "fundingEnvironment": "Tight"
    }
  ],
  "decisions": [],
  "simulationResults": [],
  "users": [
    {
      "id": 1,
      "email": "founder@example.com",
      "password": "foundr123",
      "name": "Demo Founder"
    }
  ]
}
